__init__.py
deiteo_kafka/__init__.py
deiteo_kafka/log.py
deiteo_kafka/producer/__init__.py
deiteo_kafka/producer/deiteo_kafka_aio_producer.py
deiteo_kafka_client-0.0.2a0.dist-info/WHEEL
deiteo_kafka_client-0.0.2a0.dist-info/METADATA
deiteo_kafka_client-0.0.2a0.dist-info/RECORD
