Metadata-Version: 2.1
Name: deiteo-kafka-client
Version: 0.0.2a0
Summary: Python Kafka Client Developed By Deiteo Organisation
Home-page: https://github.com/deiteo/deiteo-kafka-client
Author: Simon Thelin
Requires-Python: >=3.8,<4.0
Classifier: Programming Language :: Python :: 3
Classifier: Programming Language :: Python :: 3.10
Classifier: Programming Language :: Python :: 3.8
Classifier: Programming Language :: Python :: 3.9
Requires-Dist: aiokafka (==0.7.1)
Project-URL: Repository, https://github.com/deiteo/deiteo-kafka-client
